{
  "_meta": {
    "generated_at": "08 Jul 2026 13:12 IST",
    "source": "kite (official, live session)",
    "universe": "SECTOR_STOCKS (sector_rotation_core.py) \u2014 46 stocks / 10 sectors",
    "strategy_note": "Inna/Pham/Cianni/Unger reconstructed from short tooltip descriptions, not verified against an original spec. Educational signal engine only, not investment advice.",
    "counts": {
      "strong_buy": 0,
      "buy": 2,
      "watch": 47,
      "total": 49
    },
    "errors": {}
  },
  "HDFCBANK": {
    "signal": "WATCH",
    "buy_votes": 0,
    "weighted_votes": 0,
    "entry": 827.4,
    "sl": 804.11,
    "t1": 856.51,
    "t2": 885.62,
    "t3": 914.74,
    "pct_t1": 0,
    "strategies": {
      "Inna": "WATCH",
      "Pham": "WATCH",
      "Cianni": "WATCH",
      "Unger": "WATCH"
    },
    "sector": "Banking",
    "data_as_of": "2026-07-08",
    "data_source": "kite"
  },
  "ICICIBANK": {
    "signal": "WATCH",
    "buy_votes": 0,
    "weighted_votes": 0,
    "entry": 1396.3,
    "sl": 1359.23,
    "t1": 1442.64,
    "t2": 1488.97,
    "t3": 1535.31,
    "pct_t1": 0,
    "strategies": {
      "Inna": "NO_SIGNAL",
      "Pham": "WATCH",
      "Cianni": "WATCH",
      "Unger": "WATCH"
    },
    "sector": "Banking",
    "data_as_of": "2026-07-08",
    "data_source": "kite"
  },
  "SBIN": {
    "signal": "WATCH",
    "buy_votes": 0,
    "weighted_votes": 0,
    "entry": 1035.0,
    "sl": 1008.06,
    "t1": 1068.68,
    "t2": 1102.35,
    "t3": 1136.03,
    "pct_t1": 0,
    "strategies": {
      "Inna": "WATCH",
      "Pham": "WATCH",
      "Cianni": "NO_SIGNAL",
      "Unger": "WATCH"
    },
    "sector": "PSU Bank",
    "data_as_of": "2026-07-08",
    "data_source": "kite"
  },
  "KOTAKBANK": {
    "signal": "WATCH",
    "buy_votes": 0,
    "weighted_votes": 0,
    "entry": 376.1,
    "sl": 364.37,
    "t1": 390.76,
    "t2": 405.43,
    "t3": 420.09,
    "pct_t1": 0,
    "strategies": {
      "Inna": "NO_SIGNAL",
      "Pham": "NO_SIGNAL",
      "Cianni": "NO_SIGNAL",
      "Unger": "NO_SIGNAL"
    },
    "sector": "Banking",
    "data_as_of": "2026-07-08",
    "data_source": "kite"
  },
  "AXISBANK": {
    "signal": "WATCH",
    "buy_votes": 0,
    "weighted_votes": 0,
    "entry": 1333.4,
    "sl": 1294.91,
    "t1": 1381.51,
    "t2": 1429.62,
    "t3": 1477.74,
    "pct_t1": 0,
    "strategies": {
      "Inna": "WATCH",
      "Pham": "WATCH",
      "Cianni": "NO_SIGNAL",
      "Unger": "WATCH"
    },
    "sector": "Banking",
    "data_as_of": "2026-07-08",
    "data_source": "kite"
  },
  "TCS": {
    "signal": "WATCH",
    "buy_votes": 0,
    "weighted_votes": 0,
    "entry": 2079.6,
    "sl": 1982.68,
    "t1": 2200.75,
    "t2": 2321.9,
    "t3": 2443.05,
    "pct_t1": 0,
    "strategies": {
      "Inna": "NO_SIGNAL",
      "Pham": "NO_SIGNAL",
      "Cianni": "WATCH",
      "Unger": "NO_SIGNAL"
    },
    "sector": "IT",
    "data_as_of": "2026-07-08",
    "data_source": "kite"
  },
  "INFY": {
    "signal": "WATCH",
    "buy_votes": 0,
    "weighted_votes": 0,
    "entry": 1073.0,
    "sl": 1017.05,
    "t1": 1142.94,
    "t2": 1212.88,
    "t3": 1282.81,
    "pct_t1": 0,
    "strategies": {
      "Inna": "NO_SIGNAL",
      "Pham": "NO_SIGNAL",
      "Cianni": "NO_SIGNAL",
      "Unger": "NO_SIGNAL"
    },
    "sector": "IT",
    "data_as_of": "2026-07-08",
    "data_source": "kite"
  },
  "WIPRO": {
    "signal": "WATCH",
    "buy_votes": 0,
    "weighted_votes": 0,
    "entry": 174.84,
    "sl": 168.75,
    "t1": 182.45,
    "t2": 190.06,
    "t3": 197.68,
    "pct_t1": 0,
    "strategies": {
      "Inna": "NO_SIGNAL",
      "Pham": "NO_SIGNAL",
      "Cianni": "WATCH",
      "Unger": "NO_SIGNAL"
    },
    "sector": "IT",
    "data_as_of": "2026-07-08",
    "data_source": "kite"
  },
  "HCLTECH": {
    "signal": "WATCH",
    "buy_votes": 0,
    "weighted_votes": 0,
    "entry": 1157.9,
    "sl": 1100.3,
    "t1": 1229.9,
    "t2": 1301.9,
    "t3": 1373.9,
    "pct_t1": 0,
    "strategies": {
      "Inna": "NO_SIGNAL",
      "Pham": "NO_SIGNAL",
      "Cianni": "NO_SIGNAL",
      "Unger": "NO_SIGNAL"
    },
    "sector": "IT",
    "data_as_of": "2026-07-08",
    "data_source": "kite"
  },
  "TECHM": {
    "signal": "WATCH",
    "buy_votes": 0,
    "weighted_votes": 0,
    "entry": 1432.2,
    "sl": 1364.24,
    "t1": 1517.15,
    "t2": 1602.1,
    "t3": 1687.05,
    "pct_t1": 0,
    "strategies": {
      "Inna": "WATCH",
      "Pham": "NO_SIGNAL",
      "Cianni": "NO_SIGNAL",
      "Unger": "NO_SIGNAL"
    },
    "sector": "IT",
    "data_as_of": "2026-07-08",
    "data_source": "kite"
  },
  "MARUTI": {
    "signal": "WATCH",
    "buy_votes": 0,
    "weighted_votes": 0,
    "entry": 14295.0,
    "sl": 13794.21,
    "t1": 14920.99,
    "t2": 15546.98,
    "t3": 16172.96,
    "pct_t1": 0,
    "strategies": {
      "Inna": "NO_SIGNAL",
      "Pham": "WATCH",
      "Cianni": "WATCH",
      "Unger": "WATCH"
    },
    "sector": "Auto",
    "data_as_of": "2026-07-08",
    "data_source": "kite"
  },
  "TMPV": {
    "signal": "WATCH",
    "buy_votes": 0,
    "weighted_votes": 0,
    "entry": 339.3,
    "sl": 326.23,
    "t1": 355.64,
    "t2": 371.98,
    "t3": 388.31,
    "pct_t1": 0,
    "strategies": {
      "Inna": "NO_SIGNAL",
      "Pham": "NO_SIGNAL",
      "Cianni": "NO_SIGNAL",
      "Unger": "WATCH"
    },
    "sector": "Auto",
    "data_as_of": "2026-07-08",
    "data_source": "kite"
  },
  "M&M": {
    "signal": "WATCH",
    "buy_votes": 0,
    "weighted_votes": 0,
    "entry": 3180.0,
    "sl": 3070.15,
    "t1": 3317.31,
    "t2": 3454.62,
    "t3": 3591.94,
    "pct_t1": 0,
    "strategies": {
      "Inna": "WATCH",
      "Pham": "NO_SIGNAL",
      "Cianni": "NO_SIGNAL",
      "Unger": "WATCH"
    },
    "sector": "Auto",
    "data_as_of": "2026-07-08",
    "data_source": "kite"
  },
  "BAJAJ-AUTO": {
    "signal": "WATCH",
    "buy_votes": 1,
    "weighted_votes": 1.0,
    "entry": 10245.0,
    "sl": 9909.11,
    "t1": 10664.86,
    "t2": 11084.72,
    "t3": 11504.59,
    "pct_t1": 4.1,
    "strategies": {
      "Inna": "BUY",
      "Pham": "WATCH",
      "Cianni": "NO_SIGNAL",
      "Unger": "NO_SIGNAL"
    },
    "sector": "Auto",
    "data_as_of": "2026-07-08",
    "data_source": "kite"
  },
  "EICHERMOT": {
    "signal": "BUY",
    "buy_votes": 2,
    "weighted_votes": 2.0,
    "entry": 7584.0,
    "sl": 7310.14,
    "t1": 7926.32,
    "t2": 8268.65,
    "t3": 8610.97,
    "pct_t1": 4.5,
    "strategies": {
      "Inna": "BUY",
      "Pham": "BUY",
      "Cianni": "NO_SIGNAL",
      "Unger": "WATCH"
    },
    "sector": "Auto",
    "data_as_of": "2026-07-08",
    "data_source": "kite"
  },
  "SUNPHARMA": {
    "signal": "WATCH",
    "buy_votes": 0,
    "weighted_votes": 0,
    "entry": 1888.3,
    "sl": 1843.76,
    "t1": 1943.97,
    "t2": 1999.65,
    "t3": 2055.32,
    "pct_t1": 0,
    "strategies": {
      "Inna": "NO_SIGNAL",
      "Pham": "WATCH",
      "Cianni": "WATCH",
      "Unger": "WATCH"
    },
    "sector": "Pharma",
    "data_as_of": "2026-07-08",
    "data_source": "kite"
  },
  "DRREDDY": {
    "signal": "WATCH",
    "buy_votes": 0,
    "weighted_votes": 0,
    "entry": 1358.6,
    "sl": 1308.81,
    "t1": 1420.84,
    "t2": 1483.07,
    "t3": 1545.31,
    "pct_t1": 0,
    "strategies": {
      "Inna": "NO_SIGNAL",
      "Pham": "WATCH",
      "Cianni": "WATCH",
      "Unger": "WATCH"
    },
    "sector": "Pharma",
    "data_as_of": "2026-07-08",
    "data_source": "kite"
  },
  "CIPLA": {
    "signal": "WATCH",
    "buy_votes": 0,
    "weighted_votes": 0,
    "entry": 1452.2,
    "sl": 1408.25,
    "t1": 1507.14,
    "t2": 1562.08,
    "t3": 1617.01,
    "pct_t1": 0,
    "strategies": {
      "Inna": "NO_SIGNAL",
      "Pham": "WATCH",
      "Cianni": "WATCH",
      "Unger": "WATCH"
    },
    "sector": "Pharma",
    "data_as_of": "2026-07-08",
    "data_source": "kite"
  },
  "DIVISLAB": {
    "signal": "BUY",
    "buy_votes": 2,
    "weighted_votes": 2.0,
    "entry": 6792.0,
    "sl": 6595.23,
    "t1": 7037.96,
    "t2": 7283.93,
    "t3": 7529.89,
    "pct_t1": 3.6,
    "strategies": {
      "Inna": "BUY",
      "Pham": "BUY",
      "Cianni": "WATCH",
      "Unger": "WATCH"
    },
    "sector": "Pharma",
    "data_as_of": "2026-07-08",
    "data_source": "kite"
  },
  "AUROPHARMA": {
    "signal": "WATCH",
    "buy_votes": 0,
    "weighted_votes": 0,
    "entry": 1571.6,
    "sl": 1510.37,
    "t1": 1648.14,
    "t2": 1724.67,
    "t3": 1801.21,
    "pct_t1": 0,
    "strategies": {
      "Inna": "NO_SIGNAL",
      "Pham": "WATCH",
      "Cianni": "WATCH",
      "Unger": "WATCH"
    },
    "sector": "Pharma",
    "data_as_of": "2026-07-08",
    "data_source": "kite"
  },
  "HINDUNILVR": {
    "signal": "WATCH",
    "buy_votes": 0,
    "weighted_votes": 0,
    "entry": 2166.4,
    "sl": 2109.7,
    "t1": 2237.28,
    "t2": 2308.15,
    "t3": 2379.03,
    "pct_t1": 0,
    "strategies": {
      "Inna": "NO_SIGNAL",
      "Pham": "NO_SIGNAL",
      "Cianni": "NO_SIGNAL",
      "Unger": "NO_SIGNAL"
    },
    "sector": "FMCG",
    "data_as_of": "2026-07-08",
    "data_source": "kite"
  },
  "ITC": {
    "signal": "WATCH",
    "buy_votes": 0,
    "weighted_votes": 0,
    "entry": 284.7,
    "sl": 278.69,
    "t1": 292.21,
    "t2": 299.72,
    "t3": 307.24,
    "pct_t1": 0,
    "strategies": {
      "Inna": "NO_SIGNAL",
      "Pham": "NO_SIGNAL",
      "Cianni": "NO_SIGNAL",
      "Unger": "NO_SIGNAL"
    },
    "sector": "FMCG",
    "data_as_of": "2026-07-08",
    "data_source": "kite"
  },
  "NESTLEIND": {
    "signal": "WATCH",
    "buy_votes": 0,
    "weighted_votes": 0,
    "entry": 1467.2,
    "sl": 1425.01,
    "t1": 1519.94,
    "t2": 1572.68,
    "t3": 1625.41,
    "pct_t1": 0,
    "strategies": {
      "Inna": "NO_SIGNAL",
      "Pham": "WATCH",
      "Cianni": "NO_SIGNAL",
      "Unger": "WATCH"
    },
    "sector": "FMCG",
    "data_as_of": "2026-07-08",
    "data_source": "kite"
  },
  "BRITANNIA": {
    "signal": "WATCH",
    "buy_votes": 0,
    "weighted_votes": 0,
    "entry": 5373.5,
    "sl": 5233.95,
    "t1": 5547.94,
    "t2": 5722.38,
    "t3": 5896.81,
    "pct_t1": 0,
    "strategies": {
      "Inna": "NO_SIGNAL",
      "Pham": "NO_SIGNAL",
      "Cianni": "NO_SIGNAL",
      "Unger": "NO_SIGNAL"
    },
    "sector": "FMCG",
    "data_as_of": "2026-07-08",
    "data_source": "kite"
  },
  "DABUR": {
    "signal": "WATCH",
    "buy_votes": 0,
    "weighted_votes": 0,
    "entry": 445.3,
    "sl": 431.83,
    "t1": 462.14,
    "t2": 478.98,
    "t3": 495.81,
    "pct_t1": 0,
    "strategies": {
      "Inna": "WATCH",
      "Pham": "NO_SIGNAL",
      "Cianni": "NO_SIGNAL",
      "Unger": "NO_SIGNAL"
    },
    "sector": "FMCG",
    "data_as_of": "2026-07-08",
    "data_source": "kite"
  },
  "TATASTEEL": {
    "signal": "WATCH",
    "buy_votes": 0,
    "weighted_votes": 0,
    "entry": 189.37,
    "sl": 184.27,
    "t1": 195.75,
    "t2": 202.12,
    "t3": 208.49,
    "pct_t1": 0,
    "strategies": {
      "Inna": "NO_SIGNAL",
      "Pham": "NO_SIGNAL",
      "Cianni": "WATCH",
      "Unger": "NO_SIGNAL"
    },
    "sector": "Metal",
    "data_as_of": "2026-07-08",
    "data_source": "kite"
  },
  "JSWSTEEL": {
    "signal": "WATCH",
    "buy_votes": 0,
    "weighted_votes": 0,
    "entry": 1234.0,
    "sl": 1199.76,
    "t1": 1276.8,
    "t2": 1319.6,
    "t3": 1362.4,
    "pct_t1": 0,
    "strategies": {
      "Inna": "NO_SIGNAL",
      "Pham": "NO_SIGNAL",
      "Cianni": "NO_SIGNAL",
      "Unger": "WATCH"
    },
    "sector": "Metal",
    "data_as_of": "2026-07-08",
    "data_source": "kite"
  },
  "HINDALCO": {
    "signal": "WATCH",
    "buy_votes": 0,
    "weighted_votes": 0,
    "entry": 975.55,
    "sl": 940.88,
    "t1": 1018.89,
    "t2": 1062.22,
    "t3": 1105.56,
    "pct_t1": 0,
    "strategies": {
      "Inna": "NO_SIGNAL",
      "Pham": "WATCH",
      "Cianni": "WATCH",
      "Unger": "NO_SIGNAL"
    },
    "sector": "Metal",
    "data_as_of": "2026-07-08",
    "data_source": "kite"
  },
  "VEDL": {
    "signal": "WATCH",
    "buy_votes": 0,
    "weighted_votes": 0,
    "entry": 275.1,
    "sl": 261.99,
    "t1": 291.49,
    "t2": 307.88,
    "t3": 324.26,
    "pct_t1": 0,
    "strategies": {
      "Inna": "NO_SIGNAL",
      "Pham": "NO_SIGNAL",
      "Cianni": "WATCH",
      "Unger": "WATCH"
    },
    "sector": "Metal",
    "data_as_of": "2026-07-08",
    "data_source": "kite"
  },
  "SAIL": {
    "signal": "WATCH",
    "buy_votes": 0,
    "weighted_votes": 0,
    "entry": 164.64,
    "sl": 156.7,
    "t1": 174.56,
    "t2": 184.49,
    "t3": 194.41,
    "pct_t1": 0,
    "strategies": {
      "Inna": "NO_SIGNAL",
      "Pham": "NO_SIGNAL",
      "Cianni": "WATCH",
      "Unger": "NO_SIGNAL"
    },
    "sector": "Metal",
    "data_as_of": "2026-07-08",
    "data_source": "kite"
  },
  "RELIANCE": {
    "signal": "WATCH",
    "buy_votes": 0,
    "weighted_votes": 0,
    "entry": 1290.3,
    "sl": 1256.65,
    "t1": 1332.36,
    "t2": 1374.42,
    "t3": 1416.49,
    "pct_t1": 0,
    "strategies": {
      "Inna": "NO_SIGNAL",
      "Pham": "NO_SIGNAL",
      "Cianni": "NO_SIGNAL",
      "Unger": "NO_SIGNAL"
    },
    "sector": "Energy",
    "data_as_of": "2026-07-08",
    "data_source": "kite"
  },
  "ONGC": {
    "signal": "WATCH",
    "buy_votes": 0,
    "weighted_votes": 0,
    "entry": 242.25,
    "sl": 234.37,
    "t1": 252.1,
    "t2": 261.95,
    "t3": 271.8,
    "pct_t1": 0,
    "strategies": {
      "Inna": "NO_SIGNAL",
      "Pham": "WATCH",
      "Cianni": "WATCH",
      "Unger": "NO_SIGNAL"
    },
    "sector": "Energy",
    "data_as_of": "2026-07-08",
    "data_source": "kite"
  },
  "POWERGRID": {
    "signal": "WATCH",
    "buy_votes": 0,
    "weighted_votes": 0,
    "entry": 282.9,
    "sl": 275.87,
    "t1": 291.69,
    "t2": 300.47,
    "t3": 309.26,
    "pct_t1": 0,
    "strategies": {
      "Inna": "NO_SIGNAL",
      "Pham": "NO_SIGNAL",
      "Cianni": "NO_SIGNAL",
      "Unger": "NO_SIGNAL"
    },
    "sector": "Energy",
    "data_as_of": "2026-07-08",
    "data_source": "kite"
  },
  "NTPC": {
    "signal": "WATCH",
    "buy_votes": 0,
    "weighted_votes": 0,
    "entry": 350.8,
    "sl": 341.1,
    "t1": 362.93,
    "t2": 375.05,
    "t3": 387.17,
    "pct_t1": 0,
    "strategies": {
      "Inna": "NO_SIGNAL",
      "Pham": "NO_SIGNAL",
      "Cianni": "WATCH",
      "Unger": "NO_SIGNAL"
    },
    "sector": "Energy",
    "data_as_of": "2026-07-08",
    "data_source": "kite"
  },
  "BPCL": {
    "signal": "WATCH",
    "buy_votes": 0,
    "weighted_votes": 0,
    "entry": 305.4,
    "sl": 293.13,
    "t1": 320.74,
    "t2": 336.07,
    "t3": 351.41,
    "pct_t1": 0,
    "strategies": {
      "Inna": "NO_SIGNAL",
      "Pham": "WATCH",
      "Cianni": "NO_SIGNAL",
      "Unger": "WATCH"
    },
    "sector": "Energy",
    "data_as_of": "2026-07-08",
    "data_source": "kite"
  },
  "DLF": {
    "signal": "WATCH",
    "buy_votes": 0,
    "weighted_votes": 0,
    "entry": 651.95,
    "sl": 623.46,
    "t1": 687.56,
    "t2": 723.18,
    "t3": 758.79,
    "pct_t1": 0,
    "strategies": {
      "Inna": "NO_SIGNAL",
      "Pham": "WATCH",
      "Cianni": "WATCH",
      "Unger": "WATCH"
    },
    "sector": "Realty",
    "data_as_of": "2026-07-08",
    "data_source": "kite"
  },
  "GODREJPROP": {
    "signal": "WATCH",
    "buy_votes": 0,
    "weighted_votes": 0,
    "entry": 2056.3,
    "sl": 1979.16,
    "t1": 2152.73,
    "t2": 2249.15,
    "t3": 2345.58,
    "pct_t1": 0,
    "strategies": {
      "Inna": "NO_SIGNAL",
      "Pham": "WATCH",
      "Cianni": "WATCH",
      "Unger": "WATCH"
    },
    "sector": "Realty",
    "data_as_of": "2026-07-08",
    "data_source": "kite"
  },
  "OBEROIRLTY": {
    "signal": "WATCH",
    "buy_votes": 0,
    "weighted_votes": 0,
    "entry": 1903.0,
    "sl": 1827.85,
    "t1": 1996.94,
    "t2": 2090.88,
    "t3": 2184.81,
    "pct_t1": 0,
    "strategies": {
      "Inna": "NO_SIGNAL",
      "Pham": "WATCH",
      "Cianni": "WATCH",
      "Unger": "WATCH"
    },
    "sector": "Realty",
    "data_as_of": "2026-07-08",
    "data_source": "kite"
  },
  "PHOENIXLTD": {
    "signal": "WATCH",
    "buy_votes": 0,
    "weighted_votes": 0,
    "entry": 2064.7,
    "sl": 1979.83,
    "t1": 2170.79,
    "t2": 2276.87,
    "t3": 2382.96,
    "pct_t1": 0,
    "strategies": {
      "Inna": "NO_SIGNAL",
      "Pham": "WATCH",
      "Cianni": "WATCH",
      "Unger": "WATCH"
    },
    "sector": "Realty",
    "data_as_of": "2026-07-08",
    "data_source": "kite"
  },
  "PRESTIGE": {
    "signal": "WATCH",
    "buy_votes": 0,
    "weighted_votes": 0,
    "entry": 1663.7,
    "sl": 1589.48,
    "t1": 1756.48,
    "t2": 1849.25,
    "t3": 1942.03,
    "pct_t1": 0,
    "strategies": {
      "Inna": "NO_SIGNAL",
      "Pham": "WATCH",
      "Cianni": "WATCH",
      "Unger": "WATCH"
    },
    "sector": "Realty",
    "data_as_of": "2026-07-08",
    "data_source": "kite"
  },
  "BANKBARODA": {
    "signal": "WATCH",
    "buy_votes": 0,
    "weighted_votes": 0,
    "entry": 244.35,
    "sl": 234.02,
    "t1": 257.26,
    "t2": 270.17,
    "t3": 283.09,
    "pct_t1": 0,
    "strategies": {
      "Inna": "NO_SIGNAL",
      "Pham": "NO_SIGNAL",
      "Cianni": "NO_SIGNAL",
      "Unger": "NO_SIGNAL"
    },
    "sector": "PSU Bank",
    "data_as_of": "2026-07-08",
    "data_source": "kite"
  },
  "PNB": {
    "signal": "WATCH",
    "buy_votes": 0,
    "weighted_votes": 0,
    "entry": 102.85,
    "sl": 100.13,
    "t1": 106.25,
    "t2": 109.65,
    "t3": 113.05,
    "pct_t1": 0,
    "strategies": {
      "Inna": "NO_SIGNAL",
      "Pham": "NO_SIGNAL",
      "Cianni": "NO_SIGNAL",
      "Unger": "NO_SIGNAL"
    },
    "sector": "PSU Bank",
    "data_as_of": "2026-07-08",
    "data_source": "kite"
  },
  "CANBK": {
    "signal": "WATCH",
    "buy_votes": 0,
    "weighted_votes": 0,
    "entry": 124.58,
    "sl": 120.58,
    "t1": 129.58,
    "t2": 134.58,
    "t3": 139.58,
    "pct_t1": 0,
    "strategies": {
      "Inna": "NO_SIGNAL",
      "Pham": "NO_SIGNAL",
      "Cianni": "NO_SIGNAL",
      "Unger": "NO_SIGNAL"
    },
    "sector": "PSU Bank",
    "data_as_of": "2026-07-08",
    "data_source": "kite"
  },
  "UNIONBANK": {
    "signal": "WATCH",
    "buy_votes": 0,
    "weighted_votes": 0,
    "entry": 158.03,
    "sl": 152.97,
    "t1": 164.36,
    "t2": 170.68,
    "t3": 177.0,
    "pct_t1": 0,
    "strategies": {
      "Inna": "NO_SIGNAL",
      "Pham": "NO_SIGNAL",
      "Cianni": "NO_SIGNAL",
      "Unger": "NO_SIGNAL"
    },
    "sector": "PSU Bank",
    "data_as_of": "2026-07-08",
    "data_source": "kite"
  },
  "ZEEL": {
    "signal": "WATCH",
    "buy_votes": 0,
    "weighted_votes": 0,
    "entry": 101.4,
    "sl": 93.66,
    "t1": 111.08,
    "t2": 120.75,
    "t3": 130.43,
    "pct_t1": 0,
    "strategies": {
      "Inna": "WATCH",
      "Pham": "NO_SIGNAL",
      "Cianni": "WATCH",
      "Unger": "NO_SIGNAL"
    },
    "sector": "Media",
    "data_as_of": "2026-07-08",
    "data_source": "kite"
  },
  "SUNTV": {
    "signal": "WATCH",
    "buy_votes": 0,
    "weighted_votes": 0,
    "entry": 499.55,
    "sl": 482.94,
    "t1": 520.31,
    "t2": 541.08,
    "t3": 561.84,
    "pct_t1": 0,
    "strategies": {
      "Inna": "NO_SIGNAL",
      "Pham": "NO_SIGNAL",
      "Cianni": "NO_SIGNAL",
      "Unger": "NO_SIGNAL"
    },
    "sector": "Media",
    "data_as_of": "2026-07-08",
    "data_source": "kite"
  },
  "PVRINOX": {
    "signal": "WATCH",
    "buy_votes": 0,
    "weighted_votes": 0,
    "entry": 995.8,
    "sl": 958.99,
    "t1": 1041.81,
    "t2": 1087.82,
    "t3": 1133.84,
    "pct_t1": 0,
    "strategies": {
      "Inna": "WATCH",
      "Pham": "NO_SIGNAL",
      "Cianni": "NO_SIGNAL",
      "Unger": "NO_SIGNAL"
    },
    "sector": "Media",
    "data_as_of": "2026-07-08",
    "data_source": "kite"
  },
  "NETWORK18": {
    "signal": "WATCH",
    "buy_votes": 0,
    "weighted_votes": 0,
    "entry": 31.66,
    "sl": 30.16,
    "t1": 33.53,
    "t2": 35.41,
    "t3": 37.28,
    "pct_t1": 0,
    "strategies": {
      "Inna": "NO_SIGNAL",
      "Pham": "NO_SIGNAL",
      "Cianni": "NO_SIGNAL",
      "Unger": "NO_SIGNAL"
    },
    "sector": "Media",
    "data_as_of": "2026-07-08",
    "data_source": "kite"
  },
  "SAREGAMA": {
    "signal": "WATCH",
    "buy_votes": 0,
    "weighted_votes": 0,
    "entry": 458.75,
    "sl": 432.14,
    "t1": 492.01,
    "t2": 525.28,
    "t3": 558.54,
    "pct_t1": 0,
    "strategies": {
      "Inna": "WATCH",
      "Pham": "WATCH",
      "Cianni": "WATCH",
      "Unger": "WATCH"
    },
    "sector": "Media",
    "data_as_of": "2026-07-08",
    "data_source": "kite"
  }
}