{
  "_meta": {
    "generated_at": "07 Jul 2026 14:56 IST",
    "source": "yfinance EOD",
    "universe": "SECTOR_STOCKS (sector_rotation_core.py) \u2014 46 stocks / 10 sectors",
    "strategy_note": "Inna/Pham/Cianni/Unger reconstructed from short tooltip descriptions, not verified against an original spec. Educational signal engine only, not investment advice.",
    "counts": {
      "strong_buy": 1,
      "buy": 2,
      "watch": 46,
      "total": 49
    },
    "errors": {}
  },
  "HDFCBANK": {
    "signal": "STRONG_BUY",
    "buy_votes": 3,
    "weighted_votes": 3.0,
    "entry": 832.35,
    "sl": 809.33,
    "t1": 861.12,
    "t2": 889.9,
    "t3": 918.67,
    "pct_t1": 3.5,
    "strategies": {
      "Inna": "STRONG_BUY",
      "Pham": "WATCH",
      "Cianni": "STRONG_BUY",
      "Unger": "BUY"
    },
    "sector": "Banking",
    "data_as_of": "2026-07-07"
  },
  "ICICIBANK": {
    "signal": "WATCH",
    "buy_votes": 0,
    "weighted_votes": 0,
    "entry": 1414.9,
    "sl": 1379.33,
    "t1": 1459.36,
    "t2": 1503.83,
    "t3": 1548.29,
    "pct_t1": 0,
    "strategies": {
      "Inna": "NO_SIGNAL",
      "Pham": "WATCH",
      "Cianni": "WATCH",
      "Unger": "WATCH"
    },
    "sector": "Banking",
    "data_as_of": "2026-07-07"
  },
  "SBIN": {
    "signal": "WATCH",
    "buy_votes": 1,
    "weighted_votes": 1.0,
    "entry": 1043.0,
    "sl": 1016.5,
    "t1": 1076.12,
    "t2": 1109.25,
    "t3": 1142.38,
    "pct_t1": 3.2,
    "strategies": {
      "Inna": "BUY",
      "Pham": "WATCH",
      "Cianni": "NO_SIGNAL",
      "Unger": "WATCH"
    },
    "sector": "PSU Bank",
    "data_as_of": "2026-07-07"
  },
  "KOTAKBANK": {
    "signal": "WATCH",
    "buy_votes": 0,
    "weighted_votes": 0,
    "entry": 381.7,
    "sl": 369.96,
    "t1": 396.38,
    "t2": 411.05,
    "t3": 425.73,
    "pct_t1": 0,
    "strategies": {
      "Inna": "NO_SIGNAL",
      "Pham": "NO_SIGNAL",
      "Cianni": "NO_SIGNAL",
      "Unger": "WATCH"
    },
    "sector": "Banking",
    "data_as_of": "2026-07-07"
  },
  "AXISBANK": {
    "signal": "BUY",
    "buy_votes": 2,
    "weighted_votes": 2.0,
    "entry": 1345.3,
    "sl": 1308.49,
    "t1": 1391.31,
    "t2": 1437.32,
    "t3": 1483.34,
    "pct_t1": 3.4,
    "strategies": {
      "Inna": "BUY",
      "Pham": "WATCH",
      "Cianni": "NO_SIGNAL",
      "Unger": "BUY"
    },
    "sector": "Banking",
    "data_as_of": "2026-07-07"
  },
  "TCS": {
    "signal": "WATCH",
    "buy_votes": 0,
    "weighted_votes": 0,
    "entry": 2102.0,
    "sl": 2005.47,
    "t1": 2222.66,
    "t2": 2343.32,
    "t3": 2463.99,
    "pct_t1": 0,
    "strategies": {
      "Inna": "NO_SIGNAL",
      "Pham": "NO_SIGNAL",
      "Cianni": "WATCH",
      "Unger": "NO_SIGNAL"
    },
    "sector": "IT",
    "data_as_of": "2026-07-07"
  },
  "INFY": {
    "signal": "WATCH",
    "buy_votes": 0,
    "weighted_votes": 0,
    "entry": 1075.1,
    "sl": 1018.7,
    "t1": 1145.6,
    "t2": 1216.1,
    "t3": 1286.6,
    "pct_t1": 0,
    "strategies": {
      "Inna": "NO_SIGNAL",
      "Pham": "WATCH",
      "Cianni": "NO_SIGNAL",
      "Unger": "NO_SIGNAL"
    },
    "sector": "IT",
    "data_as_of": "2026-07-07"
  },
  "WIPRO": {
    "signal": "WATCH",
    "buy_votes": 0,
    "weighted_votes": 0,
    "entry": 173.53,
    "sl": 167.54,
    "t1": 181.02,
    "t2": 188.51,
    "t3": 195.99,
    "pct_t1": 0,
    "strategies": {
      "Inna": "NO_SIGNAL",
      "Pham": "NO_SIGNAL",
      "Cianni": "WATCH",
      "Unger": "NO_SIGNAL"
    },
    "sector": "IT",
    "data_as_of": "2026-07-07"
  },
  "HCLTECH": {
    "signal": "WATCH",
    "buy_votes": 0,
    "weighted_votes": 0,
    "entry": 1167.9,
    "sl": 1111.43,
    "t1": 1238.49,
    "t2": 1309.08,
    "t3": 1379.66,
    "pct_t1": 0,
    "strategies": {
      "Inna": "NO_SIGNAL",
      "Pham": "WATCH",
      "Cianni": "NO_SIGNAL",
      "Unger": "NO_SIGNAL"
    },
    "sector": "IT",
    "data_as_of": "2026-07-07"
  },
  "TECHM": {
    "signal": "WATCH",
    "buy_votes": 1,
    "weighted_votes": 1.0,
    "entry": 1450.0,
    "sl": 1381.15,
    "t1": 1536.06,
    "t2": 1622.12,
    "t3": 1708.19,
    "pct_t1": 5.9,
    "strategies": {
      "Inna": "STRONG_BUY",
      "Pham": "WATCH",
      "Cianni": "NO_SIGNAL",
      "Unger": "NO_SIGNAL"
    },
    "sector": "IT",
    "data_as_of": "2026-07-07"
  },
  "MARUTI": {
    "signal": "BUY",
    "buy_votes": 2,
    "weighted_votes": 2.0,
    "entry": 14551.0,
    "sl": 14066.71,
    "t1": 15156.36,
    "t2": 15761.73,
    "t3": 16367.09,
    "pct_t1": 4.2,
    "strategies": {
      "Inna": "NO_SIGNAL",
      "Pham": "WATCH",
      "Cianni": "BUY",
      "Unger": "BUY"
    },
    "sector": "Auto",
    "data_as_of": "2026-07-07"
  },
  "TMPV": {
    "signal": "WATCH",
    "buy_votes": 0,
    "weighted_votes": 0,
    "entry": 343.4,
    "sl": 326.67,
    "t1": 364.31,
    "t2": 385.22,
    "t3": 406.14,
    "pct_t1": 0,
    "strategies": {
      "Inna": "NO_SIGNAL",
      "Pham": "NO_SIGNAL",
      "Cianni": "NO_SIGNAL",
      "Unger": "NO_SIGNAL"
    },
    "sector": "Auto",
    "data_as_of": "2026-07-07"
  },
  "M&M": {
    "signal": "WATCH",
    "buy_votes": 1,
    "weighted_votes": 1.0,
    "entry": 3201.5,
    "sl": 3089.99,
    "t1": 3340.89,
    "t2": 3480.28,
    "t3": 3619.66,
    "pct_t1": 4.4,
    "strategies": {
      "Inna": "BUY",
      "Pham": "NO_SIGNAL",
      "Cianni": "NO_SIGNAL",
      "Unger": "NO_SIGNAL"
    },
    "sector": "Auto",
    "data_as_of": "2026-07-07"
  },
  "BAJAJ-AUTO": {
    "signal": "WATCH",
    "buy_votes": 1,
    "weighted_votes": 1.0,
    "entry": 10121.0,
    "sl": 9797.11,
    "t1": 10525.86,
    "t2": 10930.72,
    "t3": 11335.59,
    "pct_t1": 4.0,
    "strategies": {
      "Inna": "BUY",
      "Pham": "WATCH",
      "Cianni": "NO_SIGNAL",
      "Unger": "NO_SIGNAL"
    },
    "sector": "Auto",
    "data_as_of": "2026-07-07"
  },
  "EICHERMOT": {
    "signal": "WATCH",
    "buy_votes": 1,
    "weighted_votes": 1.0,
    "entry": 7554.0,
    "sl": 7292.84,
    "t1": 7880.45,
    "t2": 8206.9,
    "t3": 8533.35,
    "pct_t1": 4.3,
    "strategies": {
      "Inna": "BUY",
      "Pham": "WATCH",
      "Cianni": "NO_SIGNAL",
      "Unger": "WATCH"
    },
    "sector": "Auto",
    "data_as_of": "2026-07-07"
  },
  "SUNPHARMA": {
    "signal": "WATCH",
    "buy_votes": 0,
    "weighted_votes": 0,
    "entry": 1904.4,
    "sl": 1862.0,
    "t1": 1957.4,
    "t2": 2010.4,
    "t3": 2063.4,
    "pct_t1": 0,
    "strategies": {
      "Inna": "WATCH",
      "Pham": "WATCH",
      "Cianni": "WATCH",
      "Unger": "WATCH"
    },
    "sector": "Pharma",
    "data_as_of": "2026-07-07"
  },
  "DRREDDY": {
    "signal": "WATCH",
    "buy_votes": 0,
    "weighted_votes": 0,
    "entry": 1357.2,
    "sl": 1309.01,
    "t1": 1417.44,
    "t2": 1477.68,
    "t3": 1537.91,
    "pct_t1": 0,
    "strategies": {
      "Inna": "NO_SIGNAL",
      "Pham": "WATCH",
      "Cianni": "WATCH",
      "Unger": "WATCH"
    },
    "sector": "Pharma",
    "data_as_of": "2026-07-07"
  },
  "CIPLA": {
    "signal": "WATCH",
    "buy_votes": 0,
    "weighted_votes": 0,
    "entry": 1456.8,
    "sl": 1411.4,
    "t1": 1513.55,
    "t2": 1570.3,
    "t3": 1627.05,
    "pct_t1": 0,
    "strategies": {
      "Inna": "NO_SIGNAL",
      "Pham": "WATCH",
      "Cianni": "WATCH",
      "Unger": "WATCH"
    },
    "sector": "Pharma",
    "data_as_of": "2026-07-07"
  },
  "DIVISLAB": {
    "signal": "WATCH",
    "buy_votes": 1,
    "weighted_votes": 1.0,
    "entry": 6765.5,
    "sl": 6567.61,
    "t1": 7012.86,
    "t2": 7260.23,
    "t3": 7507.59,
    "pct_t1": 3.7,
    "strategies": {
      "Inna": "WATCH",
      "Pham": "BUY",
      "Cianni": "WATCH",
      "Unger": "WATCH"
    },
    "sector": "Pharma",
    "data_as_of": "2026-07-07"
  },
  "AUROPHARMA": {
    "signal": "WATCH",
    "buy_votes": 0,
    "weighted_votes": 0,
    "entry": 1586.5,
    "sl": 1525.66,
    "t1": 1662.55,
    "t2": 1738.6,
    "t3": 1814.65,
    "pct_t1": 0,
    "strategies": {
      "Inna": "NO_SIGNAL",
      "Pham": "WATCH",
      "Cianni": "WATCH",
      "Unger": "WATCH"
    },
    "sector": "Pharma",
    "data_as_of": "2026-07-07"
  },
  "HINDUNILVR": {
    "signal": "WATCH",
    "buy_votes": 1,
    "weighted_votes": 1.0,
    "entry": 2212.4,
    "sl": 2155.89,
    "t1": 2283.04,
    "t2": 2353.68,
    "t3": 2424.31,
    "pct_t1": 3.2,
    "strategies": {
      "Inna": "STRONG_BUY",
      "Pham": "NO_SIGNAL",
      "Cianni": "NO_SIGNAL",
      "Unger": "NO_SIGNAL"
    },
    "sector": "FMCG",
    "data_as_of": "2026-07-07"
  },
  "ITC": {
    "signal": "WATCH",
    "buy_votes": 0,
    "weighted_votes": 0,
    "entry": 289.2,
    "sl": 283.81,
    "t1": 295.94,
    "t2": 302.67,
    "t3": 309.41,
    "pct_t1": 0,
    "strategies": {
      "Inna": "NO_SIGNAL",
      "Pham": "NO_SIGNAL",
      "Cianni": "NO_SIGNAL",
      "Unger": "WATCH"
    },
    "sector": "FMCG",
    "data_as_of": "2026-07-07"
  },
  "NESTLEIND": {
    "signal": "WATCH",
    "buy_votes": 0,
    "weighted_votes": 0,
    "entry": 1477.6,
    "sl": 1434.89,
    "t1": 1530.99,
    "t2": 1584.37,
    "t3": 1637.76,
    "pct_t1": 0,
    "strategies": {
      "Inna": "NO_SIGNAL",
      "Pham": "WATCH",
      "Cianni": "NO_SIGNAL",
      "Unger": "WATCH"
    },
    "sector": "FMCG",
    "data_as_of": "2026-07-07"
  },
  "BRITANNIA": {
    "signal": "WATCH",
    "buy_votes": 0,
    "weighted_votes": 0,
    "entry": 5447.0,
    "sl": 5312.7,
    "t1": 5614.88,
    "t2": 5782.75,
    "t3": 5950.63,
    "pct_t1": 0,
    "strategies": {
      "Inna": "NO_SIGNAL",
      "Pham": "NO_SIGNAL",
      "Cianni": "NO_SIGNAL",
      "Unger": "NO_SIGNAL"
    },
    "sector": "FMCG",
    "data_as_of": "2026-07-07"
  },
  "DABUR": {
    "signal": "WATCH",
    "buy_votes": 1,
    "weighted_votes": 1.0,
    "entry": 454.7,
    "sl": 441.57,
    "t1": 471.11,
    "t2": 487.52,
    "t3": 503.94,
    "pct_t1": 3.6,
    "strategies": {
      "Inna": "BUY",
      "Pham": "NO_SIGNAL",
      "Cianni": "WATCH",
      "Unger": "WATCH"
    },
    "sector": "FMCG",
    "data_as_of": "2026-07-07"
  },
  "TATASTEEL": {
    "signal": "WATCH",
    "buy_votes": 0,
    "weighted_votes": 0,
    "entry": 189.99,
    "sl": 184.71,
    "t1": 196.59,
    "t2": 203.19,
    "t3": 209.79,
    "pct_t1": 0,
    "strategies": {
      "Inna": "NO_SIGNAL",
      "Pham": "WATCH",
      "Cianni": "WATCH",
      "Unger": "NO_SIGNAL"
    },
    "sector": "Metal",
    "data_as_of": "2026-07-07"
  },
  "JSWSTEEL": {
    "signal": "WATCH",
    "buy_votes": 0,
    "weighted_votes": 0,
    "entry": 1250.5,
    "sl": 1215.99,
    "t1": 1293.64,
    "t2": 1336.78,
    "t3": 1379.91,
    "pct_t1": 0,
    "strategies": {
      "Inna": "NO_SIGNAL",
      "Pham": "WATCH",
      "Cianni": "NO_SIGNAL",
      "Unger": "WATCH"
    },
    "sector": "Metal",
    "data_as_of": "2026-07-07"
  },
  "HINDALCO": {
    "signal": "WATCH",
    "buy_votes": 0,
    "weighted_votes": 0,
    "entry": 970.35,
    "sl": 933.26,
    "t1": 1016.71,
    "t2": 1063.08,
    "t3": 1109.44,
    "pct_t1": 0,
    "strategies": {
      "Inna": "NO_SIGNAL",
      "Pham": "WATCH",
      "Cianni": "WATCH",
      "Unger": "NO_SIGNAL"
    },
    "sector": "Metal",
    "data_as_of": "2026-07-07"
  },
  "VEDL": {
    "signal": "WATCH",
    "buy_votes": 0,
    "weighted_votes": 0,
    "entry": 276.4,
    "sl": 262.82,
    "t1": 293.37,
    "t2": 310.35,
    "t3": 327.32,
    "pct_t1": 0,
    "strategies": {
      "Inna": "NO_SIGNAL",
      "Pham": "WATCH",
      "Cianni": "NO_SIGNAL",
      "Unger": "NO_SIGNAL"
    },
    "sector": "Metal",
    "data_as_of": "2026-07-07"
  },
  "SAIL": {
    "signal": "WATCH",
    "buy_votes": 0,
    "weighted_votes": 0,
    "entry": 166.28,
    "sl": 158.08,
    "t1": 176.53,
    "t2": 186.78,
    "t3": 197.03,
    "pct_t1": 0,
    "strategies": {
      "Inna": "NO_SIGNAL",
      "Pham": "NO_SIGNAL",
      "Cianni": "WATCH",
      "Unger": "NO_SIGNAL"
    },
    "sector": "Metal",
    "data_as_of": "2026-07-07"
  },
  "RELIANCE": {
    "signal": "WATCH",
    "buy_votes": 0,
    "weighted_votes": 0,
    "entry": 1316.0,
    "sl": 1284.48,
    "t1": 1355.4,
    "t2": 1394.8,
    "t3": 1434.2,
    "pct_t1": 0,
    "strategies": {
      "Inna": "NO_SIGNAL",
      "Pham": "NO_SIGNAL",
      "Cianni": "NO_SIGNAL",
      "Unger": "NO_SIGNAL"
    },
    "sector": "Energy",
    "data_as_of": "2026-07-07"
  },
  "ONGC": {
    "signal": "WATCH",
    "buy_votes": 0,
    "weighted_votes": 0,
    "entry": 244.62,
    "sl": 237.03,
    "t1": 254.11,
    "t2": 263.6,
    "t3": 273.08,
    "pct_t1": 0,
    "strategies": {
      "Inna": "NO_SIGNAL",
      "Pham": "WATCH",
      "Cianni": "WATCH",
      "Unger": "NO_SIGNAL"
    },
    "sector": "Energy",
    "data_as_of": "2026-07-07"
  },
  "POWERGRID": {
    "signal": "WATCH",
    "buy_votes": 0,
    "weighted_votes": 0,
    "entry": 285.05,
    "sl": 278.13,
    "t1": 293.7,
    "t2": 302.35,
    "t3": 311.0,
    "pct_t1": 0,
    "strategies": {
      "Inna": "NO_SIGNAL",
      "Pham": "NO_SIGNAL",
      "Cianni": "NO_SIGNAL",
      "Unger": "NO_SIGNAL"
    },
    "sector": "Energy",
    "data_as_of": "2026-07-07"
  },
  "NTPC": {
    "signal": "WATCH",
    "buy_votes": 0,
    "weighted_votes": 0,
    "entry": 355.05,
    "sl": 345.4,
    "t1": 367.11,
    "t2": 379.18,
    "t3": 391.24,
    "pct_t1": 0,
    "strategies": {
      "Inna": "NO_SIGNAL",
      "Pham": "NO_SIGNAL",
      "Cianni": "WATCH",
      "Unger": "NO_SIGNAL"
    },
    "sector": "Energy",
    "data_as_of": "2026-07-07"
  },
  "BPCL": {
    "signal": "WATCH",
    "buy_votes": 1,
    "weighted_votes": 1.0,
    "entry": 315.6,
    "sl": 304.1,
    "t1": 329.98,
    "t2": 344.35,
    "t3": 358.73,
    "pct_t1": 4.6,
    "strategies": {
      "Inna": "BUY",
      "Pham": "WATCH",
      "Cianni": "NO_SIGNAL",
      "Unger": "WATCH"
    },
    "sector": "Energy",
    "data_as_of": "2026-07-07"
  },
  "DLF": {
    "signal": "WATCH",
    "buy_votes": 0,
    "weighted_votes": 0,
    "entry": 651.95,
    "sl": 624.51,
    "t1": 686.25,
    "t2": 720.55,
    "t3": 754.85,
    "pct_t1": 0,
    "strategies": {
      "Inna": "NO_SIGNAL",
      "Pham": "WATCH",
      "Cianni": "WATCH",
      "Unger": "WATCH"
    },
    "sector": "Realty",
    "data_as_of": "2026-07-07"
  },
  "GODREJPROP": {
    "signal": "WATCH",
    "buy_votes": 0,
    "weighted_votes": 0,
    "entry": 2032.7,
    "sl": 1957.11,
    "t1": 2127.19,
    "t2": 2221.68,
    "t3": 2316.16,
    "pct_t1": 0,
    "strategies": {
      "Inna": "NO_SIGNAL",
      "Pham": "WATCH",
      "Cianni": "WATCH",
      "Unger": "WATCH"
    },
    "sector": "Realty",
    "data_as_of": "2026-07-07"
  },
  "OBEROIRLTY": {
    "signal": "WATCH",
    "buy_votes": 0,
    "weighted_votes": 0,
    "entry": 1906.9,
    "sl": 1830.62,
    "t1": 2002.25,
    "t2": 2097.6,
    "t3": 2192.95,
    "pct_t1": 0,
    "strategies": {
      "Inna": "NO_SIGNAL",
      "Pham": "WATCH",
      "Cianni": "WATCH",
      "Unger": "WATCH"
    },
    "sector": "Realty",
    "data_as_of": "2026-07-07"
  },
  "PHOENIXLTD": {
    "signal": "WATCH",
    "buy_votes": 0,
    "weighted_votes": 0,
    "entry": 2075.2,
    "sl": 1988.66,
    "t1": 2183.37,
    "t2": 2291.55,
    "t3": 2399.72,
    "pct_t1": 0,
    "strategies": {
      "Inna": "NO_SIGNAL",
      "Pham": "WATCH",
      "Cianni": "WATCH",
      "Unger": "WATCH"
    },
    "sector": "Realty",
    "data_as_of": "2026-07-07"
  },
  "PRESTIGE": {
    "signal": "WATCH",
    "buy_votes": 0,
    "weighted_votes": 0,
    "entry": 1675.0,
    "sl": 1600.81,
    "t1": 1767.74,
    "t2": 1860.48,
    "t3": 1953.21,
    "pct_t1": 0,
    "strategies": {
      "Inna": "NO_SIGNAL",
      "Pham": "WATCH",
      "Cianni": "WATCH",
      "Unger": "WATCH"
    },
    "sector": "Realty",
    "data_as_of": "2026-07-07"
  },
  "BANKBARODA": {
    "signal": "WATCH",
    "buy_votes": 0,
    "weighted_votes": 0,
    "entry": 248.3,
    "sl": 237.67,
    "t1": 261.59,
    "t2": 274.88,
    "t3": 288.16,
    "pct_t1": 0,
    "strategies": {
      "Inna": "NO_SIGNAL",
      "Pham": "NO_SIGNAL",
      "Cianni": "NO_SIGNAL",
      "Unger": "NO_SIGNAL"
    },
    "sector": "PSU Bank",
    "data_as_of": "2026-07-07"
  },
  "PNB": {
    "signal": "WATCH",
    "buy_votes": 0,
    "weighted_votes": 0,
    "entry": 104.28,
    "sl": 101.56,
    "t1": 107.68,
    "t2": 111.08,
    "t3": 114.48,
    "pct_t1": 0,
    "strategies": {
      "Inna": "NO_SIGNAL",
      "Pham": "NO_SIGNAL",
      "Cianni": "NO_SIGNAL",
      "Unger": "NO_SIGNAL"
    },
    "sector": "PSU Bank",
    "data_as_of": "2026-07-07"
  },
  "CANBK": {
    "signal": "WATCH",
    "buy_votes": 0,
    "weighted_votes": 0,
    "entry": 125.15,
    "sl": 120.96,
    "t1": 130.39,
    "t2": 135.63,
    "t3": 140.86,
    "pct_t1": 0,
    "strategies": {
      "Inna": "NO_SIGNAL",
      "Pham": "NO_SIGNAL",
      "Cianni": "NO_SIGNAL",
      "Unger": "NO_SIGNAL"
    },
    "sector": "PSU Bank",
    "data_as_of": "2026-07-07"
  },
  "UNIONBANK": {
    "signal": "WATCH",
    "buy_votes": 0,
    "weighted_votes": 0,
    "entry": 161.13,
    "sl": 155.96,
    "t1": 167.59,
    "t2": 174.05,
    "t3": 180.52,
    "pct_t1": 0,
    "strategies": {
      "Inna": "NO_SIGNAL",
      "Pham": "NO_SIGNAL",
      "Cianni": "NO_SIGNAL",
      "Unger": "WATCH"
    },
    "sector": "PSU Bank",
    "data_as_of": "2026-07-07"
  },
  "ZEEL": {
    "signal": "WATCH",
    "buy_votes": 0,
    "weighted_votes": 0,
    "entry": 101.87,
    "sl": 94.03,
    "t1": 111.67,
    "t2": 121.47,
    "t3": 131.27,
    "pct_t1": 0,
    "strategies": {
      "Inna": "WATCH",
      "Pham": "NO_SIGNAL",
      "Cianni": "WATCH",
      "Unger": "WATCH"
    },
    "sector": "Media",
    "data_as_of": "2026-07-07"
  },
  "SUNTV": {
    "signal": "WATCH",
    "buy_votes": 0,
    "weighted_votes": 0,
    "entry": 508.0,
    "sl": 491.71,
    "t1": 528.36,
    "t2": 548.73,
    "t3": 569.09,
    "pct_t1": 0,
    "strategies": {
      "Inna": "NO_SIGNAL",
      "Pham": "NO_SIGNAL",
      "Cianni": "NO_SIGNAL",
      "Unger": "NO_SIGNAL"
    },
    "sector": "Media",
    "data_as_of": "2026-07-07"
  },
  "PVRINOX": {
    "signal": "WATCH",
    "buy_votes": 0,
    "weighted_votes": 0,
    "entry": 1002.2,
    "sl": 964.95,
    "t1": 1048.76,
    "t2": 1095.33,
    "t3": 1141.89,
    "pct_t1": 0,
    "strategies": {
      "Inna": "WATCH",
      "Pham": "NO_SIGNAL",
      "Cianni": "NO_SIGNAL",
      "Unger": "NO_SIGNAL"
    },
    "sector": "Media",
    "data_as_of": "2026-07-07"
  },
  "NETWORK18": {
    "signal": "WATCH",
    "buy_votes": 0,
    "weighted_votes": 0,
    "entry": 32.07,
    "sl": 30.47,
    "t1": 34.07,
    "t2": 36.07,
    "t3": 38.07,
    "pct_t1": 0,
    "strategies": {
      "Inna": "NO_SIGNAL",
      "Pham": "NO_SIGNAL",
      "Cianni": "NO_SIGNAL",
      "Unger": "NO_SIGNAL"
    },
    "sector": "Media",
    "data_as_of": "2026-07-07"
  },
  "SAREGAMA": {
    "signal": "WATCH",
    "buy_votes": 0,
    "weighted_votes": 0,
    "entry": 462.1,
    "sl": 435.86,
    "t1": 494.9,
    "t2": 527.7,
    "t3": 560.5,
    "pct_t1": 0,
    "strategies": {
      "Inna": "WATCH",
      "Pham": "WATCH",
      "Cianni": "WATCH",
      "Unger": "WATCH"
    },
    "sector": "Media",
    "data_as_of": "2026-07-07"
  }
}