{
  "fetched_at": "20 Jul 2026 16:06 IST",
  "source": "NSE official RSS (nsearchives.nseindia.com) — corporate announcements, not general market news",
  "position_news": [
    {
      "company": "Suzlon Energy Limited",
      "summary": "Suzlon Energy Limited has informed the Exchange about Board Meeting to be held on 28-Jul-2026 to inter-alia consider and approve the Unaudited Financial results of the Company for the Quarterly ended June 2026 . |SUBJECT: Board Meeting Intimation",
      "link": "https://nsearchives.nseindia.com/corporate/xbrl/PIBM_532667_207202615479_PRIOR_INTIMATION_WebXMLFile_20260720_154852673.xml",
      "published": "20-Jul-2026 15:48:53",
      "ticker": "SUZLON",
      "kind": "watchlist"
    },
    {
      "company": "VA Tech Wabag Limited",
      "summary": "VA TECH WABAG LIMITED has informed the Exchange about Bagging/Receiving of orders/contracts  (Sub-para 4-Para B) |SUBJECT: Bagging/Receiving of orders/contracts  (Sub-para 4-Para B)",
      "link": "https://nsearchives.nseindia.com/corporate/xbrl/REG30PARAB_533269_2072026103620_REG30_PARA_B_WebXMLFile_20260720_103625330.xml",
      "published": "20-Jul-2026 10:36:26",
      "ticker": "WABAG",
      "kind": "watchlist"
    },
    {
      "company": "HDFC Bank Limited",
      "summary": "Record Date Updates |SUBJECT: Record Date Updates",
      "link": "https://nsearchives.nseindia.com/content/debt/WDM/HDFCBANK2_20072026102444_RECORD_DATE_INTIMATION_TO_NSE_BSE_20072026.pdf",
      "published": "20-Jul-2026 10:25:08",
      "ticker": "HDFCBANK",
      "kind": "watchlist"
    },
    {
      "company": "HDFC Bank Limited",
      "summary": "Record Date Updates |SUBJECT: Record Date Updates",
      "link": "https://nsearchives.nseindia.com/content/debt/WDM/HDFCBANK2_20072026102444_RECORD_DATE_INTIMATION_TO_NSE_BSE_20072026.pdf",
      "published": "20-Jul-2026 10:25:08",
      "ticker": "HDFCBANK",
      "kind": "watchlist"
    },
    {
      "company": "HDFC Bank Limited",
      "summary": "Record Date Updates |SUBJECT: Record Date Updates",
      "link": "https://nsearchives.nseindia.com/content/debt/WDM/HDFCBANK2_20072026102444_RECORD_DATE_INTIMATION_TO_NSE_BSE_20072026.pdf",
      "published": "20-Jul-2026 10:25:07",
      "ticker": "HDFCBANK",
      "kind": "watchlist"
    },
    {
      "company": "HDFC Bank Limited",
      "summary": "Record Date Updates |SUBJECT: Record Date Updates",
      "link": "https://nsearchives.nseindia.com/content/debt/WDM/HDFCBANK2_20072026102444_RECORD_DATE_INTIMATION_TO_NSE_BSE_20072026.pdf",
      "published": "20-Jul-2026 10:25:07",
      "ticker": "HDFCBANK",
      "kind": "watchlist"
    },
    {
      "company": "HDFC Bank Limited",
      "summary": "Record Date Updates |SUBJECT: Record Date Updates",
      "link": "https://nsearchives.nseindia.com/content/debt/WDM/HDFCBANK2_20072026102444_RECORD_DATE_INTIMATION_TO_NSE_BSE_20072026.pdf",
      "published": "20-Jul-2026 10:25:06",
      "ticker": "HDFCBANK",
      "kind": "watchlist"
    },
    {
      "company": "Larsen & Toubro Limited",
      "summary": "Larsen & Toubro Limited has informed the Exchange about Bagging/Receiving of orders/contracts |SUBJECT: Bagging/Receiving of orders/contracts",
      "link": "https://nsearchives.nseindia.com/corporate/PAM_20072026090928_PressRelease20072026.pdf",
      "published": "20-Jul-2026 09:09:48",
      "ticker": "LT",
      "kind": "watchlist"
    },
    {
      "company": "Divi's Laboratories Limited",
      "summary": "Divi's Laboratories Limited has informed the Exchange about Board Meeting to be held on 01-Aug-2026 to inter-alia consider and approve the Unaudited Financial results of the Company for the Quarterly ended June 2026 . |SUBJECT: Board Meeting Intimation",
      "link": "https://nsearchives.nseindia.com/corporate/xbrl/BM_IntimationQ1FY27_20072026_PRIOR_INTIMATION_WebXMLFile_20260720_090057445.xml",
      "published": "20-Jul-2026 09:00:58",
      "ticker": "DIVISLAB",
      "kind": "watchlist"
    },
    {
      "company": "VA Tech Wabag Limited",
      "summary": "WABAG Secures Large Order Inflow from BWSSB for Two Energy-Efficient Wastewater Treatment Facilities |SUBJECT: Bagging/Receiving of orders/contracts",
      "link": "https://nsearchives.nseindia.com/corporate/VATECH_20072026063902_SIBWSSB20July26.pdf",
      "published": "20-Jul-2026 06:44:52",
      "ticker": "WABAG",
      "kind": "watchlist"
    }
  ],
  "recent_announcements": [
    {
      "company": "Godrej Consumer Products Limited",
      "summary": "Godrej Consumer Products Limited has informed the Exchange about Copy of Newspaper Publication |SUBJECT: Copy of Newspaper Publication",
      "link": "https://nsearchives.nseindia.com/corporate/GODREJCP_20072026160356_GCPL_SE_Intimation_-_Loss_of_Share_Cert-signed.pdf",
      "published": "20-Jul-2026 16:05:14"
    },
    {
      "company": "Wanbury Limited",
      "summary": "Wanbury Limited has informed the Exchange about General Updates |SUBJECT: General Updates",
      "link": "https://nsearchives.nseindia.com/corporate/WANBURY_20072026160457_Intimation.pdf",
      "published": "20-Jul-2026 16:05:08"
    },
    {
      "company": "Trom Industries Limited",
      "summary": "Submission of SDD Compliance Certificates for the Quarter ended on 30th June, 2026 |SUBJECT: Structural Digital Database",
      "link": "https://nsearchives.nseindia.com/corporate/TROM2024_20072026160455_SDD_Trom.pdf",
      "published": "20-Jul-2026 16:05:06"
    },
    {
      "company": "Bansal Wire Industries Limited",
      "summary": "BANSAL WIRE INDUSTRIES LIMITED has informed the Exchange about Schedule of Analysts or Institutional Investors Meet |SUBJECT: Analyst/Investor Meet Para A-XBRL",
      "link": "https://nsearchives.nseindia.com/corporate/xbrl/SAIIM_544209_207202616419_SAIIM_WebXMLFile_20260720_160423606.xml",
      "published": "20-Jul-2026 16:04:25"
    },
    {
      "company": "Technocraft Industries (India) Limited",
      "summary": "Technocraft Industries (India) Limited has informed the Exchange about closure of fabric division located at Murbad |SUBJECT: General Updates",
      "link": "https://nsearchives.nseindia.com/corporate/TIIL_20072026160354_upload.pdf",
      "published": "20-Jul-2026 16:04:13"
    },
    {
      "company": "Tvs Credit Services Limited",
      "summary": "Statement of utilization of issue proceeds |SUBJECT: Statement of utilization of issue proceeds",
      "link": "https://nsearchives.nseindia.com/content/debt/WDM/tvscs2008_20072026160147_TVSCSNSE527.pdf",
      "published": "20-Jul-2026 16:02:24"
    },
    {
      "company": "Vivid Electromech Limited",
      "summary": "The Exchange had sought clarification from Vivid Electromech Limited for the quarter ended 31-Mar-2026 with respect to Regulation 33 of the SEBI (Listing Obligations and Disclosure Requirements) Regulations, 2015. On basis of above the Company was required to clarify the following:   The response of the Company is enclosed. |SUBJECT: Reply to Clarification- Financial results",
      "link": "https://nsearchives.nseindia.com/corporate/VIVID_03072026153551_Clarification_Letter_.pdf",
      "published": "20-Jul-2026 16:02:22"
    },
    {
      "company": "Parsvnath Developers Limited",
      "summary": "PARSVNATH DEVELOPERS LIMITED has informed the Exchange about Corporate Insolvency Resolution Process for the event related to Prior or Post-facto intimation of the meetings of Committee of Creditors |SUBJECT: Corporate Insolvency Resolution Process-XBRL",
      "link": "https://nsearchives.nseindia.com/corporate/xbrl/CIRP_532780_207202616035_CIRP_WebXMLFile_20260720_160207546.xml",
      "published": "20-Jul-2026 16:02:08"
    },
    {
      "company": "Hdfc Securities Limited",
      "summary": "Record Date Updates |SUBJECT: Record Date Updates",
      "link": "https://nsearchives.nseindia.com/content/debt/WDM/HDFC2_20072026160155_INE700G14TL4_NSE.pdf",
      "published": "20-Jul-2026 16:02:08"
    },
    {
      "company": "Chemplast Sanmar Limited",
      "summary": "CHEMPLAST SANMAR LIMITED has informed the Exchange about Action(s) taken or orders passed (sub-para 20) |SUBJECT: Actions initiated/taken or orders passed-XBRL",
      "link": "https://nsearchives.nseindia.com/corporate/xbrl/AIATOP_543336_207202616128_AIATOP_WebXMLFile_20260720_160153105.xml",
      "published": "20-Jul-2026 16:01:54"
    },
    {
      "company": "Pfizer Limited",
      "summary": "PFIZER LIMITED has informed the Exchange about Board Meeting to be held on 28-Jul-2026 to inter-alia consider and approve the Unaudited Financial results of the Company for the Quarterly ended June 2026 . |SUBJECT: Board Meeting Intimation",
      "link": "https://nsearchives.nseindia.com/corporate/xbrl/PIBM_500680_207202616030_PRIOR_INTIMATION_WebXMLFile_20260720_160145834.xml",
      "published": "20-Jul-2026 16:01:46"
    },
    {
      "company": "Salasar Exteriors and Contour Limited",
      "summary": "Salasar Exteriors And Contour Limited has informed the Exchange regarding Outcome of Board Meeting held on July 20, 2026. |SUBJECT: Outcome of Board Meeting",
      "link": "https://nsearchives.nseindia.com/corporate/SECL_20072026160053_Outcome_of_BM.pdf",
      "published": "20-Jul-2026 16:01:41"
    },
    {
      "company": "OM INFRA LIMITED",
      "summary": "OM INFRA LIMITED has informed the Exchange about Awarding of order(s)/contract(s)-(Sub-para 4-Para B) |SUBJECT: Awarding of order(s)/contract(s)-(Sub-para 4-Para B)",
      "link": "https://nsearchives.nseindia.com/corporate/xbrl/REG30PARAB_531092_20072026_REG30_PARA_B_WebXMLFile_20260720_160106557.xml",
      "published": "20-Jul-2026 16:01:07"
    },
    {
      "company": "Bansal Wire Industries Limited",
      "summary": "Bansal Wire Industries Limited has informed the Exchange about Schedule of Earnings conference Call to dicuss the financial results for the first quarter ended June 30, 2026 to be held on Thursday, July 23, 2026 at 11:00 A.M. IST |SUBJECT: Analysts/Institutional Investor Meet/Con. Call Updates",
      "link": "https://nsearchives.nseindia.com/corporate/BANSALWIRE_20072026155918_Schedule_of_Investor_Meet_Q1_FY27.pdf",
      "published": "20-Jul-2026 15:59:46"
    },
    {
      "company": "Best Agrolife Limited",
      "summary": "Best Agrolife Limited has informed the Exchange about Copy of Newspaper Publication-communication to shareholders |SUBJECT: Copy of Newspaper Publication",
      "link": "https://nsearchives.nseindia.com/corporate/BESTAGRO_20072026155757_SE_Reg_30_Unpaid_DIv_200726.pdf",
      "published": "20-Jul-2026 15:58:37"
    }
  ],
  "feed_errors": {
    "Board_Meetings": "HTTPSConnectionPool(host='nsearchives.nseindia.com', port=443): Read timed out. (read timeout=15)"
  },
  "tracked_positions": [],
  "tracked_watchlist": [
    "ADANIGREEN",
    "ARE&M",
    "ASIANPAINT",
    "BAJFINANCE",
    "DIVISLAB",
    "EXIDEIND",
    "HDFCBANK",
    "HINDUNILVR",
    "ICICIBANK",
    "INFY",
    "IONEXCHANG",
    "JSWENERGY",
    "KOTAKBANK",
    "LT",
    "MARUTI",
    "NESTLEIND",
    "NTPCGREEN",
    "OLECTRA",
    "PIDILITIND",
    "PREMIERENE",
    "SUNPHARMA",
    "SUZLON",
    "TATAPOWER",
    "TCS",
    "TITAN",
    "TMPV",
    "WAAREEENER",
    "WABAG",
    "WEBELSOLAR"
  ],
  "disclaimer": "Corporate filings/announcements only (results, board meetings, trading-window closures, etc.), not macro/general market news. General-news API integration deferred — see NEXT UPGRADE in script docstring."
}